odoo/addons/account_fiscal_position_rule_purchase/README.rst
odoo/addons/account_fiscal_position_rule_purchase/__init__.py
odoo/addons/account_fiscal_position_rule_purchase/__manifest__.py
odoo/addons/account_fiscal_position_rule_purchase/i18n/account_fiscal_position_rule_purchase.pot
odoo/addons/account_fiscal_position_rule_purchase/i18n/es.po
odoo/addons/account_fiscal_position_rule_purchase/i18n/pt_BR.po
odoo/addons/account_fiscal_position_rule_purchase/i18n/sl.po
odoo/addons/account_fiscal_position_rule_purchase/models/__init__.py
odoo/addons/account_fiscal_position_rule_purchase/models/purchase.py
odoo/addons/account_fiscal_position_rule_purchase/readme/CONTRIBUTORS.rst
odoo/addons/account_fiscal_position_rule_purchase/readme/DESCRIPTION.rst
odoo/addons/account_fiscal_position_rule_purchase/static/description/icon.png
odoo/addons/account_fiscal_position_rule_purchase/static/description/index.html
odoo/addons/account_fiscal_position_rule_purchase/tests/__init__.py
odoo/addons/account_fiscal_position_rule_purchase/tests/test_account_fiscal_position_rule_purchase.py
odoo13_addon_account_fiscal_position_rule_purchase-13.0.1.0.1.dev4.dist-info/METADATA
odoo13_addon_account_fiscal_position_rule_purchase-13.0.1.0.1.dev4.dist-info/WHEEL
odoo13_addon_account_fiscal_position_rule_purchase-13.0.1.0.1.dev4.dist-info/top_level.txt
odoo13_addon_account_fiscal_position_rule_purchase-13.0.1.0.1.dev4.dist-info/RECORD
